odoo8_addon_mail_connector_queue-8.0.1.0.1.99.dev7-py3.8-nspkg.pth
odoo_addons/mail_connector_queue/README.rst
odoo_addons/mail_connector_queue/__init__.py
odoo_addons/mail_connector_queue/__openerp__.py
odoo_addons/mail_connector_queue/hooks.py
odoo_addons/mail_connector_queue/job.py
odoo_addons/mail_connector_queue/i18n/ca.po
odoo_addons/mail_connector_queue/i18n/de.po
odoo_addons/mail_connector_queue/i18n/es.po
odoo_addons/mail_connector_queue/i18n/es_CO.po
odoo_addons/mail_connector_queue/i18n/fi.po
odoo_addons/mail_connector_queue/i18n/fr.po
odoo_addons/mail_connector_queue/i18n/hr.po
odoo_addons/mail_connector_queue/i18n/hu.po
odoo_addons/mail_connector_queue/i18n/it.po
odoo_addons/mail_connector_queue/i18n/lv.po
odoo_addons/mail_connector_queue/i18n/mail_connector_queue.pot
odoo_addons/mail_connector_queue/i18n/nb.po
odoo_addons/mail_connector_queue/i18n/nl.po
odoo_addons/mail_connector_queue/i18n/pt.po
odoo_addons/mail_connector_queue/i18n/pt_BR.po
odoo_addons/mail_connector_queue/i18n/sl.po
odoo_addons/mail_connector_queue/i18n/sv.po
odoo_addons/mail_connector_queue/i18n/th.po
odoo_addons/mail_connector_queue/i18n/zh_CN.po
odoo_addons/mail_connector_queue/models/__init__.py
odoo_addons/mail_connector_queue/models/mail_mail.py
odoo_addons/mail_connector_queue/readme/CONTRIBUTORS.rst
odoo_addons/mail_connector_queue/readme/DESCRIPTION.rst
odoo_addons/mail_connector_queue/readme/HISTORY.rst
odoo_addons/mail_connector_queue/readme/USAGE.rst
odoo_addons/mail_connector_queue/static/description/icon.png
odoo_addons/mail_connector_queue/static/description/index.html
odoo_addons/mail_connector_queue/views/mail_mail.xml
odoo8_addon_mail_connector_queue-8.0.1.0.1.99.dev7.dist-info/METADATA
odoo8_addon_mail_connector_queue-8.0.1.0.1.99.dev7.dist-info/WHEEL
odoo8_addon_mail_connector_queue-8.0.1.0.1.99.dev7.dist-info/namespace_packages.txt
odoo8_addon_mail_connector_queue-8.0.1.0.1.99.dev7.dist-info/top_level.txt
odoo8_addon_mail_connector_queue-8.0.1.0.1.99.dev7.dist-info/RECORD
